infrablocks/invoke_factory/dynamic_task.py
infrablocks/invoke_factory/py.typed
infrablocks_invoke_factory-0.0.2.dist-info/LICENSE.md
infrablocks_invoke_factory-0.0.2.dist-info/METADATA
infrablocks_invoke_factory-0.0.2.dist-info/WHEEL
infrablocks_invoke_factory-0.0.2.dist-info/RECORD
