Metadata-Version: 2.1
Name: infrablocks.invoke_factory
Version: 0.0.2
Summary: Base classes and modules to aid in creating custom invoke tasks.
License: MIT
Author: Toby Clemson
Author-email: tobyclemson@gmail.com
Requires-Python: >=3.13,<4.0
Classifier: License :: OSI Approved :: MIT License
Classifier: Programming Language :: Python :: 3
